mailer.py
setup.py
mailer3.egg-info/PKG-INFO
mailer3.egg-info/SOURCES.txt
mailer3.egg-info/dependency_links.txt
mailer3.egg-info/top_level.txt