Metadata-Version: 1.1
Name: mailer3
Version: 0.1
Summary: A copy of https://pypi.python.org/pypi/mailer with 2to3 run over all the .py files.
Home-page: https://github.com/joedborg/mailer
Author: Joe Borg
Author-email: UNKNOWN
License: MIT License
Keywords: email,smtp
Platform: UNKNOWN
Classifier: Programming Language :: Python :: 3
